cub/__init__.py
cub/compat.py
cub/config.py
cub/exceptions.py
cub/models.py
cub/timezone.py
cub/transport.py
cub/version.py
cub-0.28.0.dist-info/LICENSE
cub-0.28.0.dist-info/METADATA
cub-0.28.0.dist-info/WHEEL
cub-0.28.0.dist-info/top_level.txt
cub-0.28.0.dist-info/RECORD
